pupil_labs/realtime_api/__init__.py
pupil_labs/realtime_api/audio_player.py
pupil_labs/realtime_api/base.py
pupil_labs/realtime_api/device.py
pupil_labs/realtime_api/discovery.py
pupil_labs/realtime_api/models.py
pupil_labs/realtime_api/py.typed
pupil_labs/realtime_api/time_echo.py
pupil_labs/realtime_api/simple/__init__.py
pupil_labs/realtime_api/simple/_utils.py
pupil_labs/realtime_api/simple/device.py
pupil_labs/realtime_api/simple/discovery.py
pupil_labs/realtime_api/simple/models.py
pupil_labs/realtime_api/streaming/__init__.py
pupil_labs/realtime_api/streaming/au_unit.py
pupil_labs/realtime_api/streaming/audio.py
pupil_labs/realtime_api/streaming/base.py
pupil_labs/realtime_api/streaming/eye_events.py
pupil_labs/realtime_api/streaming/gaze.py
pupil_labs/realtime_api/streaming/imu.py
pupil_labs/realtime_api/streaming/nal_unit.py
pupil_labs/realtime_api/streaming/video.py
aiortsp/__init__.py
aiortsp/__version__.py
aiortsp/rtcp/__init__.py
aiortsp/rtcp/parser.py
aiortsp/rtcp/stats.py
aiortsp/rtsp/__init__.py
aiortsp/rtsp/auth.py
aiortsp/rtsp/connection.py
aiortsp/rtsp/errors.py
aiortsp/rtsp/parser.py
aiortsp/rtsp/reader.py
aiortsp/rtsp/sdp.py
aiortsp/rtsp/session.py
aiortsp/transport/__init__.py
aiortsp/transport/base.py
aiortsp/transport/tcp.py
aiortsp/transport/udp.py
pupil_labs_realtime_api-1.7.3.dist-info/METADATA
pupil_labs_realtime_api-1.7.3.dist-info/WHEEL
pupil_labs_realtime_api-1.7.3.dist-info/licenses/LICENSE
pupil_labs_realtime_api-1.7.3.dist-info/RECORD
