Metadata-Version: 2.4
Name: pupil-labs-realtime-api
Version: 1.7.3
Summary: Python Client for the Pupil Labs Real-Time API
Project-URL: Homepage, https://pupil-labs.github.io/pl-realtime-api
Project-URL: Documentation, https://pupil-labs.github.io/pl-realtime-api
Project-URL: Repository, https://github.com/pupil-labs/pl-realtime-api
Project-URL: Issues, https://github.com/pupil-labs/pl-realtime-api/issues
Project-URL: Network API Specification, https://github.com/pupil-labs/realtime-network-api
Author-email: Pupil Labs GmbH <info@pupil-labs.com>
License: MIT
License-File: LICENSE
Classifier: Development Status :: 5 - Production/Stable
Classifier: Intended Audience :: Developers
Classifier: License :: OSI Approved :: MIT License
Classifier: Programming Language :: Python :: 3.10
Classifier: Programming Language :: Python :: 3.11
Classifier: Programming Language :: Python :: 3.12
Classifier: Programming Language :: Python :: 3.13
Classifier: Topic :: Software Development :: Libraries :: Python Modules
Requires-Python: <4.0,>=3.10
Requires-Dist: aiohttp[speedups]>=3.11.14
Requires-Dist: av>=14.2.0
Requires-Dist: beaupy>=3.10.1
Requires-Dist: deprecated>=1.2.18
Requires-Dist: dpkt>=1.9.8
Requires-Dist: numpy
Requires-Dist: pupil-labs-neon-recording>=2.0.0
Requires-Dist: pupil-labs-video>=1.0.3
Requires-Dist: pydantic>=2.10.6
Requires-Dist: sounddevice>=0.5.2
Requires-Dist: websockets>=15.0.1
Requires-Dist: zeroconf>=0.146.1
